{"songs": [{"title": "Crowded Tub", "album": null, "year": null, "lyrics": "It's a song for a shitty sad, really bad situation\nLittle ditty for the man who doesn't think he'll smile no more\nI keep bouncin' at the beach and chillin' with the choir of good times\nBest I can give you is a little piece of good advice\n\nThat's oooooo what did you say and\nHeeeeyyyyy what can you do\nOoooo life's tough to play\nAnd Heyyyyy what can you do?", "image": "https://assets.genius.com/images/default_cover_image.png?1573677821"}], "artist": "Perpetual Groove"}