{"songs": [{"title": "Ma belle blonde", "album": "M\u00eame pas mal !", "year": null, "lyrics": "Ma cage thoracique est bien\nTrop petite\nMes petits poumons sont bien\nTrop \u00e9troit\nPour respirer cet aire qui\nSent le souffle qui m'essouffle\nPour aspirer un un avenir\nQui expire entre toi et moi\n\nMa volont\u00e9 et bien trop sport adique\nEt mon petit corps et bien trop adique\nPour crapoter l'aire que tu me souffle m\u00eame si j'\u00e9touffe\nPour me d\u00e9cider \u00e0 en finir avec ce d\u00e9sir d'une derni\u00e8re fois\n\nCar m\u00eame si j'ai les boules ma belle\nNotre amours doit prendre fin ici\nEt m\u00eame si j'ai la trouille ma vieille\nTu ne l'emporta pas tu ne m'emportera pas au paradis\n\nNotre amours si grand devient\nPath\u00e9tique\nEt mon c\u0153ur si noir ralentis tic tac tic\nOn ne reculera pas l'heure fatale qui s'installe\nTu ne passera pas l'hiver\nMais entre mes deux doigts tu continue a faire la fi\u00e8re\n\nTu me dit que mes discours son\nFam\u00e9lique\nQue mes belles paroles ne sont que\nRh\u00e9torique\nTu m'embrassera a la moindre faille\nPour un d\u00e9taille\nMoi j'embrasserais tes formes conique\nAvec mes poumons en plastique\n\nCar m\u00eame si j'ai les boules ma belle\nNotre amours doit prendre fin ici\nEt m\u00eame si j'ai la trouille ma vieille\nTu ne l'emporta pas tu ne m'emportera pas au paradis\n\nTu \u00e9tait blonde et belle dans ta robe bleu\nMa jolie demoiselle\nT'aurait pas du feu\nTu danse telle une gitane\nUn derni\u00e8re fois ma gauloise\nCe soir je te condamne\nC'est sous mes pieds\nQue je t'\u00e9crase\n\nEt m\u00eame si j'ai les boules ma belle\nNotre amours prendre fin ici\nEt m\u00eame si j'ai la trouille ma vieille\nTant pis je cloperais au paradis\n\nCar m\u00eame si j'ai les boules ma belle\nNotre amours doit prendre fin ici\nEt m\u00eame si j'ai la trouille ma vieille\nTu ne l'emporta pas tu ne m'emportera pas au paradis", "image": "https://assets.genius.com/images/default_cover_image.png?1573677821"}], "artist": "Les Tit\u2019 Nassels"}