{"songs": [{"title": "La Decisi\u00f3n", "album": "Ekhymosis", "year": null, "lyrics": "Nunca me dijeron que todo andaba mal, lo se\nY nunca fue mi culpa, no quererlo averiguar por eso\nAndo recogiendo mil pedazos de este coraz\u00f3n que\nNo le sirve ya sangre de otro coraz\u00f3n\n\nPero fue la decisi\u00f3n, no tuve nada, nada que decir\nSe fueron de mi vida as\u00ed, y yo no lo puedo entender\n\nPasan los segundos que parecen una eternidad\nPasa esta cancion para que sepas que aun estoy aqu\u00ed\n\nY pasa mi voz can't\u00e1ndote\nY pasa el amor cort\u00e1ndome\n\nY pasan los a\u00f1os que me llevar\u00e1n\nLejos de t\u00ed\n\nSolamente quedan los recuerdos en la vida\nSolamente queda una salida, no la olvides\n\nCon el tiempo todo llega a su final\nHoy me toc\u00f3 aprender a mi\nNo me vas a derrotar\nEl cielo se derrama en mi\n\nNo me importa cuanto vales, se que ahora no me vales\nY no es para lastimarte, es solo para olvidarte\nPara odiarte y borrarte de mi mente para siempre\nSin cadenas en mis manos\nSin cadenas en mi alma\nLa vida le da al que no quiere mas\nY a mi me dio poco de t\u00ed", "image": "https://images.genius.com/74b065fe638f13f61a5c355b31bd6ff6.953x953x1.jpg"}], "artist": "Ekhymosis"}