{"songs": [{"title": "Te hubieras ido antes", "album": null, "year": null, "lyrics": "No existe amor perfecto\nEmpiezo a pensar que\nEsto del amor es una fantas\u00eda\nY no me la creo\nQue tu ya no te acuerdes\nDe todas las veces\nQue te hice.. mia\nY todavia me exiges\nQue olvide tu sonrisa\nY borre de mi mente todas tus caricias\nMe subes hasta el cielo\nY luego caigo al suelo\nPorque tu te vas cuando mas te quer\u00eda\nTe hubieras ido antes\nPor que no te marchaste\nCuando aun no eras tan indispensable?\nMe pides que te olvide\nCuando hiciste todo para enamorarme\nAun que estabas jugando dime\nPor que diablos me obligaste a amarte\nY luego te alejaste?\nTe hubieras ido antes\nNo creo que merezca que\nMi coraz\u00f3n tires a la basura\nMe suena tan il\u00f3gico\nQue ahora digas que no fue tu culpa\nSi no te interesaba pa' que me besabas\nCon tanta dulzura y con tanta ternura\nTe hubieras ido antes\nY as\u00ed ya no tendr\u00eda\nEstas ganas de rogarte\nY todavia me exiges\nQue olvide tu sonrisa\nY borre de mi mente todas tus caricias\nMe subes hasta el cielo\nY luego caigo al suelo\nPorque tu te vas\nCuando mas te quer\u00eda\nTe hubieras ido antes\nPor que no te marchaste\nCuando aun no eras tan indispensable?\nMe pides que te olvide\nCuando hiciste todo para enamorarme\nAun que estabas jugando dime\nPor que diablos me obligaste a amarte\nY luego te alejaste?\nTe hubieras ido antes\nNo creo que merezca que\nMi coraz\u00f3n tires a la basura\nMe suena tan il\u00f3gico\nQue ahora digas que no fue tu culpa\nSi no te interesaba pa' que me besabas\nCon tanta dulzura y con tanta ternura\nTe hubieras ido antes\nY as\u00ed ya no tendr\u00eda\nEstas ganas de rogarte", "image": "https://images.genius.com/eeff33dfb07cc2eb1e60a925ae543f55.382x382x1.jpg"}], "artist": "Moderatto"}