{"songs": [{"title": "Sweet Gwendoline", "album": "Memento Mori", "year": null, "lyrics": "Geknebelt und fest gebunden\nLiegst du hier schon seit Stunden\nDas Dunkel l\u00e4sst dich erblinden\nDu f\u00fchlst die Hoffnung schwinden\nUnd du wei\u00dft du bist verloren\nDenn der Meister (Harrharr) hat dich auserkoren\n\nMit dem Schicksal abgefunden\nDreh'n Gedanken ihre Runden\nLust und Schmerz macht dich benommen\nPhantasien, wie noch nie ersonnen\nUnd du wei\u00dft, du bist verloren\nDenn der Meister (Herr, Herr) hat dich auserkoren\n\nScham l\u00e4sst dich err\u00f6ten\nDer Trieb wird die W\u00fcrde t\u00f6ten\nKeine Zeit mehr zum entrinnen\nKeine Kraft dich zu besinnen\nUnd du wei\u00dft du bist verloren\n\nGwendoline, du bist auserkoren\nTonight, Sweet Gwendoline\nDo it well and do it fine\nTonight, Sweet Gwendoline\nDo it well and do it fine\nTonight, Sweet Gwendoline\nDo it well and do it fine\n\nDu gibst nach, du l\u00e4sst dich fallen\nDu, die sch\u00f6nste Frau von allen\nDas Spiel wird dich nicht schonen\nDoch die Nacht wird dich belohnen\nDu bist erw\u00e4hlt, du bist verloren\nGwendoline, du bist auserkoren\n\nTonight, Sweet Gwendoline\nDo it well and do it fine\nTonight, Sweet Gwendoline\nDo it well and do it fine\nTonight, Sweet Gwendoline\nDo it well and do it fine\n\nTonight, Sweet Gwendoline\nTonight, Sweet Gwendoline", "image": "https://images.genius.com/34739d6b68d787c1a9cdf63301c19dba.500x500x1.jpg"}], "artist": "Umbra Et Imago"}