{"songs": [{"title": "Aventuras Y Proezas", "album": "Parvadomus", "year": null, "lyrics": "Aventuras y proezas de una simple capital\nY voy por la ruta de lo pirados\nY en cada esquina siempre encuertro algun colgado\nY como el diablo con sus ofertas\nLo unico que ofresco es tomarse una cervesa\nY un par de orejas pa'l que lo escuchen\nTocar un tema seguido de unos buches\nSer sincero, ser bien claro\n'tamo todo los que somos,somos todos los que estamos\n'tamo todos locos muy de la mente\nDesbundados hasta los dientes\nAchincados a tocar con los tiros\nQue caiga la noche y hacer la del vampiro\nChuparnos todo menos la sangre\nY agitar hasta que uno se desarme\nPero nunca olvidar lo de todo los dias\nParvadomus al once le dio vida\n\nY que mas y que mas y que mas puedo pedir........\nY que mas y que mas y que mas puedo decir........\n\nAventuras y proezas de una simple capital\nY voy por la ruta de lo pirados\nY en cada esquina siempre encuertro algun colgado\nY como el diablo con sus ofertas\nLo unico que ofresco es tomarse una cervesa\nY un par de orejas pa'l que lo escuchen\nTocar un tema seguido de unos buches\nSer sincero, ser bien claro\n'tamo todo los que somos,somos todos los que estamos\n'tamo todos locos muy de la mente\nDesbundados hasta los dientes\nAchincados a tocar con los tiros\nQue caiga la noche y hacer la del vampiro\nChuparnos todo menos la sangre\nY agitar hasta que uno se desarme\nPero nunca olvidar lo de todo los dias\n\nY que mas y que mas y que mas puedo pedir........\nY que mas y que mas y que mas puedo pedir........", "image": "https://images.genius.com/996ffc64ab3dd542ea5f97211a324a50.350x350x1.jpg"}], "artist": "Once Tiros"}