{"songs": [{"title": "Brief", "album": null, "year": "2017-04-14", "lyrics": "Briefe, meist entstehn' sie, wenn die andern gehn\nDieser hier auch, nur verwischt die Schrift dank meinen Tr\u00e4nen\nFrag mich nicht wie es mir geht, sondern wie ich's aushalt\nSteh ich auf dem Gleis, f\u00fchlt sich's an als w\u00fcrd ich schon bald nach Haus fahrn\nIch m\u00f6cht nur ein verdammtes mal in meinem schei\u00df Leben Ruhe haben\nNur einmal in meinem Leben m\u00f6chte ich in ruhe schlafen\nIch glaube echt, dass ich so langsam den Verstand verlier'\nDenn umso l\u00e4nger du schon tot bist, w\u00e4chst dann mein Verlangen nach dir\nMein einziges Verlangen dich wieder in meine Arme zu schlie\u00dfen\nVerlangen zu schlafen, weil die Probleme einfach zu viel sind\nDas Verlangen nichts mehr in sich zu fressen\nWas f\u00fcr frei, ich sitz schon viel zu lange in mir selbst in Ketten\nSteh schon wieder auf der Br\u00fccke doch das komische ist\nW\u00fcrd' ich spring, w\u00fcrd' ich alle verlassen, so wie du mich\nDas sind die letzten Worte, das ist das Ende des Briefs\nDie Welt ist frei, doch ich bin mir leider selbst das Verlies\n\nIch schreib damit du wei\u00dft, wie es mir geht hier unten\nDenn seitdem du weg bist verl\u00e4uft mein verdammter Weg ins Dunkle\nUnd ich schreibe diesen Brief damit du wei\u00dft\nDass sich nichts von alldem schei\u00df ver\u00e4ndert hat mit der Zeit\nIch bin immer noch wie damals, immer noch zu broke\nStell mir t\u00e4glich die Frage: Warum hat Gott mich nicht verschont?\nIch bin immer noch wie damals, immer noch zu broke\nIch bin immer noch der selbe, nur eben als Misanthrop\n\nIch hab mag Menschen nicht du fragst nach dem Grund?\nSie sagen du hast dich ver\u00e4ndert, doch keiner dich fragt warum\n(Warum?)\nSchon leicht komisch, wie alles auf einmal grau erscheint\nUnd egal wie stark man versucht zu l\u00e4cheln, die Trauer bleibt\nIch will nur schreiben was mich so alles gepr\u00e4gt hat\nIch will nur, dass jemand das hier jemand lie\u00dft und vielleicht mich verstehn' kann\nUnd wenn das niemand tut, dann ist das auch egal\nDenn bisher schaffte ich das auch alleine unter tausend Qualen. Ich laufe taumelnd durch den Regen doch ich schaff das schon\nUnd sollte ich nicht stark genug sein, ja dann lass ich los\nIch meine was ist schon dabei einfach tsch\u00fcss zu sagen?\nDann h\u00e4tt' man nicht diese Gedanken schon am fr\u00fchen Abend\nNur ein Atemzug und ich stell mich aufs Ger\u00fcst\nWie viele Tage hab ich mir das alles hier schon gew\u00fcnscht?\nSchlie\u00dfe meine Augen, lasse los, denn der Hass sitzt tief\nDas hier sind meine letzten Worte - Nenn' es Abschiedsbrief\n\nIch schreib damit du wei\u00dft, wie es mir geht hier unten\nDenn seitdem du weg bist verl\u00e4uft mein verdammter Weg ins Dunkle\nUnd ich schreibe diesen Brief damit du wei\u00dft\nDass sich nichts von alldem schei\u00df ver\u00e4ndert hat mit der Zeit\nIch bin immer noch wie damals, immer noch zu broke\nStell mir t\u00e4glich die Frage: Warum hat Gott mich nicht verschont?\nIch bin immer noch wie damals, immer noch zu broke\nIch bin immer noch der selbe, nur eben als Misanthrop", "image": "https://images.genius.com/4e286b5bd450ed19c9c57437a4d66ec9.640x640x1.jpg"}], "artist": "Example"}