{"songs": [{"title": "A Cigarette is All You Get", "album": "Give Yourself a Hand", "year": null, "lyrics": "I'm all freaked out\nI'm all tweaked out\nI'm being chased by insects\nAnd I wanna eat my cigarettes\nI can't hang out\nI'm all strung out\nI've got to grab me by the throat\nI've got to herd me like a goat\n\nA cigarette is all you get\nSo hold your fire, don't light it yet\n\nI'm all mixed up\nI gotta fix me up\nI wanna pull my tongue out\nAnd turn my nostrils inside out\nI'm all dried up\nI'm all fried up\nI wanna burn things now and then\nIf I've been talkin' to businessmen\n\nA cigarette is all you get\nSo hold your fire, don't light it yet\n\nI'm all shook up\nI wanna get hooked up\nI wanna listen to Elvis\nI wanna shake my pelvis\nI wanna take the train downtown\nI wanna hear some Junior Brown\nI wanna move my groovy hips\nI wanna bite my shaky lips\n\nA cigarette is all you get\nSo hold your fire, don't light it yet", "image": "https://images.genius.com/053c70181ac1ec50a1116c1a9ad67aa4.953x953x1.jpg"}], "artist": "Crash Test Dummies"}