{"songs": [{"title": "Pennies From Heaven", "album": null, "year": null, "lyrics": "A long time ago, about a million years B.C\nThe best things in life were absolutely free\nBut no one appreciated a sky that was always blue\nAnd no one anticipated a moon that was always new\n\nSo it was planned that they should vanish now and then\nAnd you must pay before you get them back again\nThat's what storms were made for\nAnd you shouldn't be afraid for\n\nEvery time it rains, it rains, pennies from heaven\nDon't you know each cloud contains pennies from heaven?\nYou'll find your fortune's falling all over the town\nMake sure that your umbrella is upside down\n\nTrade them for a package of sunshine and flowers\nIf you want the things you love, you must have showers\nSo, when you hear it thunder, don't run under a tree\nThere'll be pennies from heaven for you and me\n\nEvery time it rains, it rains pennies from heaven\nDon't you know each cloud contains pennies from heaven?\nYou'll find your fortune's falling all over the town\nMake sure that your umbrella is upside down\n\nTrade them for a package of sunshine and flowers\nIf you want the things you love, you must have showers\nSo, when you hear it thunder, don't run under a tree\nThere'll be pennies from heaven for you and me\n\nSo take a big deep breath of the clean fresh air\nPut a smile on your face, be a millionaire\nThe streets outside are paved with gold\nThere'll be pennies from heaven for you and me", "image": "https://assets.genius.com/images/default_cover_image.png?1573677821"}], "artist": "The Mills Brothers"}