{"songs": [{"title": "She Was Five and He Was Ten", "album": null, "year": null, "lyrics": "She was five and he was ten\nTwice as old as she was then\nShe was much too young for him, in puppy love\n\nAs the years went rolling by\nHe was fifteen and quite a guy\nBut she was ten, still too young for him to love\n\nAnd then, as he grew older\nHe changed his point of view\nWhen she was seventeen, he was only twenty-two\n\nSo he fell in love, you see\nAnd it all began when she\nWas only five and he was ten, in puppy love\n\nAnd then, as he grew older\nHe changed his point of view\nWhen she was seventeen, he was only twenty-two\n\nSo he fell in love, you see\nAnd it all began when she\nWas only five and he was ten in puppy love, puppy love", "image": "https://assets.genius.com/images/default_cover_image.png?1573677821"}], "artist": "The Mills Brothers"}