{"songs": [{"title": "\u200bmother/HOLDS", "album": "bi/MENTAL", "year": "2019-02-01", "lyrics": "[Intro]\nAhh!\n\n[Verse 1]\nMy mother holds my new born child\nShe's covered in tape\nStillborn asthma\nShe whimpers as they hold her\nThe coughing ensues\n\n[Pre-Chorus]\nSo give me milk without any panic attacks\nSo give me milk without any panic attacks\nMany panic, any panic\n\n[Chorus]\nMother holds my only lifeline\nMother holds my only lifeline\nMother holds my only lifeline\nWon't you take her away?\nPlace her under the flatline\n\n[Verse 2]\nMy triumph holds my only lifeline\nThis marrow has doubt\nAsphalt liar\nI keep on falling flat-faced\nI'm simmered in mud\n\n[Pre-Chorus]\nSo give me milk without any panic attacks\nSo give me milk without any panic attacks\nMany panic, any panic\n\n[Chorus]\nMother holds my only lifeline\nMother holds my only lifeline\nMother holds my only lifeline\nWon't you take her away?\nPlace her under the flatline\n\n[Bridge]\nShe was a spider while roaming the streets\nWon't you have mercy on me?\nOnce was a tiger hunting Poseidon\nWon't you have pity on me?\n\n[Chorus]\nMother holds my only lifeline\nMother holds my only lifeline\nMother holds my only lifeline\nWon't you take her away?\nPlace her under the flatline\nMother holds my only lifeline\nMother holds my only lifeline\nMother holds my only lifeline\nWon't you take her away?\nPlace her under the flatline", "image": "https://images.genius.com/f11e2001729d975eee6482aaf0a8a2b8.1000x1000x1.png"}], "artist": "Le Butcherettes"}