{"songs": [{"title": "La Vieja Llama", "album": "Pura vida", "year": null, "lyrics": "Vuelvo a empezar\nVuelvo a cantar\nVuelvo a avivar la vieja llama\nVoy a evitar lo que me hace mal\nY me entrego en cuerpo y alma\n\nComenzando a caminar\nDe la nada al amas all\u00e1\nCada paso que voy dando\nMe doy vuelta a contemplar\nY el camino que ahi est\u00e1\nAlej\u00e1ndose hacia atr\u00e1s\nY mi voz quiere aclarar\n\nVuelvo a empezar\nVuelvo a cantar\nVuelvo a avivar la vieja llama\nVoy a evitar lo que me hace mal\nY me entrego en cuerpo y alma\n\nHoy y ayer\nSiempre la misma pregunta\nQue ahora cuesta responder\nSi hubo un antes y un despues\nUn derecho y un rev\u00e9s\nLa canci\u00f3n vuelve a crecer\n\nVuelvo a empezar\nVuelvo a cantar\nVuelvo a avivar la vieja llama\nVoy a evitar lo que me hace mal\nY me entrego en cuerpo y alma\n\nSi la meta no es llegar\nY el destino es solo andar\nSin dudarlo voy por mas\n\nNo es dif\u00edcil de explicar\nSolo me dej\u00e9 llevar\nY al final comprendo todo\n\nVuelvo a empezar\nVuelvo a cantar\nVuelvo a avivar esa llama\nVuelvo a empezar\nVuelvo a cantar\nVuelvo a avivar esa llama\nVuelvo a cantar\nEsa llama\u2026\nVuelvo a avivar esa llama\nVuelvo a empezar\nVuelvo a cantar\nVuelvo a avivar esa llama", "image": "https://images.genius.com/7fe9db6fb4faf5aab65bf04e733bbb59.1000x1000x1.jpg"}], "artist": "Los Pericos"}