{"songs": [{"title": "Libido (En Vivo)", "album": null, "year": null, "lyrics": "Nos vimos de nuevo, pensaste en volver a m\u00ed\nMe tienes contigo, no sabes lo que aprend\u00ed\n\nA llorar sin l\u00e1grimas\nA no creer en los sue\u00f1os\nA no envolverme en tus besos, ni en tus caricias\nPorque todas son mentiras\n\nY te quito las ropas\nY yo entro en tu cuerpo\nY juntando las almas, tu cuerpo y el m\u00edo\nSe envuelven en libido\n\nTermin\u00f3 tu sue\u00f1o\nDe ser la due\u00f1a de m\u00ed\nEmpieza tu infierno\nTu premio a lo que aprend\u00ed\n\nNo quiero verte jam\u00e1s con \u00e9l\nEl odio en mi alma se pone de pie\nCon un arma en la mano no s\u00e9 que ir\u00e9 a hacer", "image": "https://s3.amazonaws.com/filepicker-images-rapgenius/5ars11TweAf25epdDUkw_27.jpg"}], "artist": "Libido"}