{"songs": [{"title": "Ella Se Mueve Cruel", "album": "Kamikaze", "year": null, "lyrics": "Oh!\n\nCon la quito que va azotando cuando llega\nElla rompe el silencio pa-kan\nPor eso ella sigue siendo la suprema\nLa insaciable la mas grande la numero one\nAhora sigo yo mi asunto voy pa\u2019 lante\nY me pregunto si esto es un pecado mortal\n\nY ella tiene lo que quiero, lo que busco lo que anhelo\nMi perversi\u00f3n total\n\nElla se mueve cruel\nElla lo bate bien\nY ser sacude bien sucio\nElla se mueve cruel\n\nElla se mueve cruel\nMira esa yala be\nTe lo restriega bien rico\nElla se mueve cruel\n\nElla se mueve cruel\nElla lo bate bien\nY ser sacude bien sucio\nElla se mueve cruel\n\nElla se mueve cruel\nMira esa yala be\nTe lo restriega bien rico\nElla se mueve cruel\n\nTu y yo tremenda punchazon\nQuiero que me bajes el siper del pantal\u00f3n\nRom\u00e1ntico siempre he sido yo\nLo que a reggae party con demencia y acci\u00f3n\n\nCuando yo te toco suavecito (aa)\nCuando yo te doy dos tres besitos(aa)\nSoy tu lover guay bien exquisito\nTodas bailan bien pero ella si se mueve cruel\n\nElla se mueve cruel\nElla lo bate bien\nY ser sacude bien sucio\nElla se mueve cruel\n\nElla se mueve cruel\nMira esa yala be\nTe lo restriega bien rico\nElla se mueve cruel\n\nElla se mueve cruel\nElla lo bate bien\nY ser sacude bien sucio\nElla se mueve cruel\n\nElla se mueve cruel\nMira esa yala be\nTe lo restriega bien rico\nElla se mueve cruel\n\nM\u00edranos en el elevador\nLevantar\u00eda tu falda en el piso dos\nSoy un cabr\u00f3n un mago de la acci\u00f3n\nSe\u00f1or de las tinieblas una revelaci\u00f3n\n\nTiene el movimiento de un $%\u2022$ de cadera\nElla es la envidia del mentado local\nPero a ella no le importa que digan lo que quieran\nPorque ella si que baila, ella si se mueve cruel\n\nElla se mueve cruel\nElla lo bate bien\nY ser sacude bien sucio\nElla se mueve cruel\n\nElla se mueve cruel\nMira esa yala be\nTe lo restriega bien rico\nElla se mueve cruel\n\nElla se mueve cruel\nElla lo bate bien\nY ser sacude bien sucio\nElla se mueve cruel\n\nElla se mueve cruel\nMira esa yala be\nTe lo restriega bien rico\nElla se mueve cruel", "image": "https://assets.genius.com/images/default_cover_image.png?1573677821"}], "artist": "Los Rabanes"}