{"songs": [{"title": "Veneno", "album": "Ecos Punzantes del Ayer", "year": null, "lyrics": "En el borde seductor\nNo hay nada m\u00e1s hermoso que t\u00fa\n\nMi vida mas oscura\nDe d\u00eda el sue\u00f1o y el cemento\nLuego entra el deseo\nSin duda\n\nInsasiablemente desnuda\nInsasiablemente desnuda\n\nTu test de fuego...\nMe llev\u00f3 al delirio\nSale el humo, entra el smoke\nCuanto da\u00f1o hay guardado\nEn tu boca mortal, tus labios\n\nInsasiablemente desnuda\nInsasiablemente desnuda\nInsasiablemente desnuda\nInsasiablemente...\n\nPuedes danzar\nCual serpiente danzar\nEl son del veneno\nQue mi coraz\u00f3n se inclina\nA tu sentencia\nEs la hora de la victoria\nEres digna de estar aqu\u00ed\n\nInsasiablemente desnuda\nInsasiablemente desnuda\nInsasiablemente desnuda\nInsasiablemente...", "image": "https://assets.genius.com/images/default_cover_image.png?1573677821"}], "artist": "Zapato 3"}