{"songs": [{"title": "No Llegas A M\u00ed", "album": "Aunque cueste ver el sol", "year": null, "lyrics": "Tu llanto no tiene sentido\nSi ya no est\u00e1s aqu\u00ed\nNo queda m\u00e1s remedio que vivir\nS\u00f3lo vivir\nMi canto no llega a tu o\u00eddo\nVos no lleg\u00e1s a m\u00ed\nSi a\u00fan te queda algo por decir\nNo lo dec\u00eds\nCuerpo tras cuerpo se van\nY adivinan despu\u00e9s\nQue sin razones no se puede sonre\u00edr\nPero para qu\u00e9 volver\nTe obligaron a seguir un camino\nOtra vez\nTe invitan a que cambies de destino y otra vez", "image": "https://images.genius.com/fefc4eb95cd91d9626b6bd3fa6ba566e.1000x1000x1.jpg"}], "artist": "No Te Va Gustar"}