{"songs": [{"title": "Empiezo A Llover", "album": "Mini / Multi", "year": null, "lyrics": "Camina para atras,Ven hacia aca Ven Hacia Mi\nQue aqui en mis brazos se encuentra tu destino\n\nEsscucho Mi Coraz\u00f3n\nA ver que es lo que Dice\nEscucho Mi Coraz\u00f3n\nA ver Si Estas ahi\nEmpiezo a llover\nY No Estas Aquiii\nEmpiezo a Llover\nEsta Lluvia Es Para Tiii\nAzul Violeta Empiezo a Llover Lyrics\n\nEmpiezo a Llover\nY No Estas Aquii\nEmpiezo a Llover\nEsta Lluvia Es Para Tiii\n\nY No Te Atrevas A Dudar,Si Mi Amor Es De Verdad\nY Nuestros Sue\u00f1os Nunca Fueron Mas Que Eso\n\nY Escucha Tu Coraz\u00f3n\nY Dime Que Te Dice\nEscucha Tu Coraz\u00f3n\nY Dime Si Yo Estoy Ahiii\nHeee\u00a1\n\nEmpiezo a llover\nY No Estas Aquiii\nEmpiezo a Llover\nEsta Lluvia Es Para Tiii\n\nEmpiezo a llover\nY No Estas Aquiii\nEmpiezo a Llover\nEsta Lluvia Es Para Tiii\n\nEmpiezo a llover\nY No Estas Aquiii\nEmpiezo a Llover\nEsta Lluvia Es Para Tiii\n\nY No Estas Aquiiiiii\nY No Estas Aquiiiii\nY No Estas Aquiiiiii\nY No Estas Aquiiiiii\nY No Estas Aquiiiiii\nY No Estas Aquiiiiii\nY No Estas Aquiiiiii", "image": "https://images.genius.com/9ce4b2b9aec37b36da6e3b397bd0c572.992x960x1.jpg"}], "artist": "Azul Violeta"}