{"songs": [{"title": "Afuera", "album": "El nervio del volc\u00e1n", "year": null, "lyrics": "[Letra de \"Afuera\"]\n\n[Verso 1]\nMuchos a\u00f1os uno cree\nQue el caer es levantarse\nY de repente... Ya no te paras\nQue el amor es temporal\nQue todo te puede pasar\nY de repente... Est\u00e1s muy solo\n\n[Coro]\nAfuera...\nAfuera t\u00fa no existes, s\u00f3lo adentro\nAfuera...\nAfuera no te cuido, s\u00f3lo adentro\nAfuera...\nTe desbarata el viento sin dudarlo\nAfuera...\nNadie es nada, s\u00f3lo adentro\n\n[Verso 2]\nSiguen los a\u00f1os y uno est\u00e1\nCreyendo que puede rezar\nY de repente... Ya te perdiste\nY uno cree que puede creer\nY tener todo el poder\nY de repente... No tienes nada\n\n[Coro]\nAfuera...\nAfuera t\u00fa no existes, s\u00f3lo adentro\nAfuera...\nAfuera no te cuido, s\u00f3lo adentro\nAfuera...\nTe desbarata el viento sin dudarlo\nAfuera...\nNadie es nada, s\u00f3lo adentro\n\n[Puente]\nA-a-ah...\nAh-ah...\n(Instrumental)\n\n[Coro]\nAfuera...\nAfuera t\u00fa no existes, s\u00f3lo adentro\nAfuera...\nAfuera no te cuido, s\u00f3lo adentro\nAfuera...\nTe desbarata el viento sin dudarlo\nAfuera...\nNadie es nada, s\u00f3lo adentro\n\n[Outro]\nAh-ah...", "image": "https://images.genius.com/8da6de351b8229e5a3b0d4e950af903c.599x615x1.jpg"}], "artist": "Caifanes"}