{"songs": [{"title": "La Vida Nos Acerca", "album": "Consejo", "year": null, "lyrics": "Lo miras con quien estar\u00e1 hoy te tengo ma\u00f1ana te iras\nPero se que no olvidaras los momentos que vivimos\nY cuando est\u00e9s ausente te llevare en mi mente\n\nCuando est\u00e9s lejos de aqu\u00ed no pares de so\u00f1ar\nNo pares de re\u00edr de buscar la raz\u00f3n y encontraras\nRespuestas\n\nQuiero seguir en alg\u00fan lugar\nDe tu coraz\u00f3n y tu mente\nPues tu luz en mi brillara\nPues en tus manos es mi suerte\nTe veras presente entre toda la gente\n\nY cuando est\u00e9s lejos de aqu\u00ed no pares de so\u00f1ar\nNo pares de re\u00edr de buscar la raz\u00f3n y encontraras\nRespuestas el mundo da mil vueltas la vida nos acerca\n\nCuando est\u00e9s lejos de aqu\u00ed no pares de so\u00f1ar\nNo pares de re\u00edr de buscar la raz\u00f3n y encontraras\nRespuestas el mundo da mil vueltas la vida nos acerca\n\nCuando est\u00e9s lejos de aqu\u00ed no pares de so\u00f1ar\nNo pares de re\u00edr de buscar la raz\u00f3n y encontraras\nRespuestas el mundo da mil vueltas la vida nos acerca\n\nCuando est\u00e9s lejos de aqu\u00ed no pares de so\u00f1ar\n(adonde vas y como estas viviendo)\nNo pares de re\u00edr de buscar la raz\u00f3n y encontraras\n(te gusta la vida)\nRespuestas el mundo da mil vueltas la vida nos acerca\nEl mundo da mil vueltas la vida nos acerca", "image": "https://images.genius.com/e49fd5d93730efff09e6677bedf92640.500x500x1.jpg"}], "artist": "La Secta Allstar"}