{"songs": [{"title": "Que El Viento Borr\u00f3 Tus Manos", "album": "Almendra", "year": "1969-11-29", "lyrics": "[Letra de \"Que El Viento Borr\u00f3 Tus Manos\"]\n\nEra una chica que vol\u00f3\nVio florecer la luz del sol\nY no volvi\u00f3\nEl tiempo comenz\u00f3 a pasar\nLas frutas no brillaron m\u00e1s\nY el sol se fue, y llovi\u00f3\nDonde estas ahora\nQue el viento borr\u00f3 tus manos\nD\u00f3nde est\u00e1s ahora\nTu cara es muy gris\nTu imagen se va\nTemprano fue el atardecer\nEl patio no la llama m\u00e1s\nEn su lugar\nQuiz\u00e1s est\u00e9 sentada aqu\u00ed\nEn una silla de algod\u00f3n\nPara mirar y mirar", "image": "https://images.genius.com/6311b812d44083d731baf2ecad949856.631x631x1.jpg"}], "artist": "Almendra"}