{"songs": [{"title": "Peque\u00f1a Caja", "album": "Compost", "year": null, "lyrics": "Estuve a punto de decirte hoy\nNo queda que celebrar\nDespu\u00e9s de haber tirado en esas lunas\nEl siglo llegara al final\nNo quieras sostenerlo\n\nAh\u00ed parado bajo el tragaluz\nBusco la cara al calor\nBajo la c\u00fapula lleg\u00f3 otro invierno\nSaliendo de la sombra cambi\u00f3\nYa quiero sostenerlo\n\nUno arma la versi\u00f3n\nEso es un buen remedio\nUno arma la versi\u00f3n\n\nEn una caja vi a un alguacil\nSuelto es un vuelo en mayo\nY busca el cielo, busca el cielo\nBusca el cielo, busca el cielo por m\u00ed\n\nDeja que queme este viejo papel\nNo importa nada se va\nEsto siglo quedara resuelto\nO por donde ahora vamos a empezar\n\nEn una caja vi a un alguacil\nSuelto es un vuelo en mayo\nY busca el cielo\nEn una caja algo para m\u00ed\nAbre alas en mayo\nY busca el cielo, busca el cielo\nBusca el cielo, busca el cielo por m\u00ed", "image": "https://images.genius.com/1059a0b3cd76f5caa1a1afaf9dceb3f7.1000x1000x1.jpg"}], "artist": "Cielo Razzo"}