{"songs": [{"title": "En el pa\u00eds del olvido", "album": null, "year": null, "lyrics": "Parece todo tranquilo\nParece que todo esta muy bien\nPero hay algo en el aire\nQue no me gusta y que no se que es\nDe vez en cuando lo pienso y nunca logro entender\nTodas las cosas que pasaron y se olvidaron a la vez\n\nLa gente de la inundacion\nLa famosa cifra de desaparicion\n\nCuantas historias por contar, de un pueblo tan golpeado\nQue ya no sabe ni como esta, ni donde vamos a parar\n\nDe mentiras nos llenaron, la informacion nos negaron\nPero la memoria siempre esta para no dejar de luchar\n\nPor las victimas del rocanrol\nPor las lagrimas del dolor\nPor la gente de la inundacion\nLa famosa cifra de desaparicion\n\nPor la gente de la inundacion\nLa famosa cifra de desaparicion\nPor las victimas del (roncanrol)\nPor las lagrimas del dolor", "image": "https://assets.genius.com/images/default_cover_image.png?1573677821"}], "artist": "La Beriso"}