{"songs": [{"title": "Nada de tu amor", "album": null, "year": null, "lyrics": "TU ERAS EN MI VIDA\nLO QUE YO SO\u00d1E\nERAS TU EL ANGEL\nQUE YO ADIVINE\n\nY NUNCA PENSE QUE FUERAS ASI\nHOY DE MI CARI\u00d1O\nYA NADA TENDRAS\n\nNO, NO LO HUBIERAS HECHO\nSIN ANTES PENSAR\nQUE YO TE QUERIA\nQUE MI CORAZON ERA SOLO TUYO\nY CON NUESTRO AMOR\nFUIMOS FELICES\nSIEMPRE LOS DOS\n\nNO YA NO QUIERO NADA\nNADA DE ESTE AMOR\nQUE ME DISTE TU\nSI ESTE ES MI DESTINO\nY ME DUELE TANTO\nNO QUIERO TU AMOR\n\nHOY LLORANDO ME PIDES\nQUE VUELVA HACIA TI\nQUE PERDONE TODO\nQUE TU CORAZON\nNO PODRIA VIVIR YA MAS SIN MI AMOR\nPERO YA ES MUY TARDE\nY YA NO PODRE\n\nNO YA NO QUIERO NADA ETC...\nLA LARARARARARA LARARARARA ETC", "image": "https://assets.genius.com/images/default_cover_image.png?1573677821"}], "artist": "Los solitarios"}