{"songs": [{"title": "No Somos Nadie", "album": "Callejeros (Demo)", "year": null, "lyrics": "Tres acordes suenan y ya est\u00e1 todo bien\nYa empieza la comparsa de que sos rock-star\nPero el rocanrol no te d\u00e1 esos privilegios\n\nQue mentira grande que te logran meter\nMorf\u00e1ndote libracos de cultura rock\nEsa gente linda se caga de risa de vos\n\nA ver si entendes\nAunque te lo creas no somos nadie\nY que le vamos a hacer\n\nSi alguien se levanta cuando vos ya quebr\u00e1s\nY se rompe los huesos para poder safar\nDenme ya un espejo a ver que estrella me llam\u00e1s\n\nTres acordes suenan y ya est\u00e1 todo bien\nYa empieza todo el circo de que sos rock-star\nPero el rocanrol no te d\u00e1 esos privilegios\n\nA ver si entendes\nAunque te lo creas no somos nadie\nY que le vamos a hacer\n\nSi alguien se levanta cuando vos ya quebr\u00e1s\nY se rompe los huesos para poder safar\nDenme ya un espejo haber que estrella me llam\u00e1s\n\nA ver si entend\u00e9s\nAunque te lo creas no somos nadie\nY que le vamos a hacer\n\nA ver si entend\u00e9s\nAunque te lo creas no somos nadie\nY que le vamos a hacer\n\n\u00bfQue le vamos a hacer?\nSi no somos nadie\n\u00bfQue le vamos a hacer?\n\n\u00bfQue le vamos a hacer?\nSi no somos nadie\n\u00bfQue le vamos a hacer?", "image": "https://images.genius.com/7698d92ed8c6cedf6c81713d3575ea56.500x500x1.jpg"}], "artist": "Callejeros"}