{"songs": [{"title": "Es importante", "album": "Hijos del Culo", "year": null, "lyrics": "...Te voy a decir algo importante\nEs importante:\nPrimordial, muy necesario\nJe je je je\nEs importante:\nJa! Allez-y\nFundamental\nEs importante\n.......................\nEs importante:\nEscaparse a alg\u00fan lugar\n\nEs importante\nCaminar por la cornisa\nY caer a toda prisa\nEn la madeja del error\nY no me achico aunque no parezca cierto\nAbran bien los ojos tuertos\nQue ha llegado un perdedor\n\nEs importante:\nQue nada sea seguro\nEs importante:\nSalir a corretear\nEs importante:\nNo llegar a ning\u00fan lado\nEs importante:\nEscapar a alg\u00fan lugar\n\nEs importante:\nVender cara la derrota\nQue me vi\u00f3, cara de idiota?\nYo tambi\u00e9n quiero ganar\nY si vale o no vale\nNo me importa\nSomos parte de esta torta\nY a pelear con dignidad\n\nEs importante:\nDejar la vida boba\nEs importante:\nNo dejarse encaminar\nEs importante:\nSi hago trampa no me importa\nY es importante\nEquivocarse una vez m\u00e1s\n\nEs importante:\nPa'que el fuego no se muera\nSacar siempre el diablo afuera\nAconsejo este ritual\nCon otra geta enmudecer garganta rota\nRomper siempre las pelotas\nSi nac\u00ed para irritar\n\nEs importante:\nDame un huesito vieja\nEs importante:\nUn bizcocho pa' mojar\nEs importante:\nQue no me dejen afuera\nEs importante:\nYa estoy para jugar\n\nEs importante:\nRenovar el deseo\nEs importante:\nPoderte extra\u00f1ar\nSoplar bien fuerte\nPa'que el fuego no se muera\nEs importante:\nOtra fiesta lo de Juan\n\nEsta familia se ha juntado nuevamente\nY ha tomado los lugares por asalto una vez m\u00e1s\n\nY as\u00ed vivimos cuerpo a cuerpo en la comparsa\nSi esta vida es una farsa\nQue regrese el carnaval\n\nEs importante:\nQue regrese el carnaval\nEs importante:\nNo dejar de corretear\n\nEs importante:\nExorcisar el maleficio\nY sacarle un beneficio\nA esta desgracia universal\n\nEs importante:\nQue no dejen de cantar\nEs importante:\nNo dejar de corretear\n\nY as\u00ed vivimos cuerpo a cuerpo en la comparsa\nSi esta vida es una farsa\nQue regrese el carnaval\nQue regrese el carnaval\n\nY as\u00ed vivimos cuerpo a cuerpo en la comparsa\nSi esta vida es una farsa\nQue regrese el carnaval\nQue regrese el carnaval", "image": "https://images.genius.com/0d594c590109cf2add702ed799435271.945x945x1.jpg"}], "artist": "Bersuit Vergarabat"}