{"songs": [{"title": "Locomotion", "album": "La Hija de la L\u00e1grima", "year": null, "lyrics": "Every body is moving like a fish in the ocean\nCome on baby to the locomotion\nEvery body is grooving when a I losing the motion\nCome on baby to the locomotion\nBut if you love me baby\nYou can send me free\nBut if you love me baby\nYou can send me free\nCome on, come on to the locomotion with me\nIf is so find...\nCome on baby to the locomotion\nCome on baby to the locomotion\nBut if you love me baby\nYou can send me free\nBut if you love me baby\nYou can dance with me\nIf si so find so baby come on\nTo the locomotion", "image": "https://images.genius.com/7e5d60c7fa9758dff23805d47c304c07.500x500x1.jpg"}], "artist": "Charly Garc\u00eda"}