{"songs": [{"title": "Cachito", "album": "\u00bfD\u00f3nde Jugar\u00e1n Los Ni\u00f1os?", "year": null, "lyrics": "Tan solo un adicto\nUn adicto de tu Sol\nY es que con solo un cachito\nUn pedacito de tu luz\nYo llegar\u00eda al cielo\nO me caer\u00eda al suelo\nPor ti amor\n\nTan solo\nUn cachito de tu coraz\u00f3n\nUn cachito de tu coraz\u00f3n\nUn cachito de tu coraz\u00f3n\nSoy un adicto de tu coraz\u00f3n\n\nPedirle a mi cabeza\nQue deje de pensar en t\u00ed\nEs casi como pedirle\nA mi coraz\u00f3n que deje de latir\nMas bien olvida eso\nNo no repitas eso, te pido amor\n\nTan solo\nUn cachito de tu coraz\u00f3n\nUn cachito de tu coraz\u00f3n\nUn cachito de tu coraz\u00f3n\nSoy un adicto de tu coraz\u00f3n\n\nChiquitita de mi coraz\u00f3n\nChiquitita de mi coraz\u00f3n\nChiquitita de mi coraz\u00f3n\nChiquitita de mi coraz\u00f3n", "image": "https://images.genius.com/38b915e5150db55e831db8d9acc73f01.1000x1000x1.jpg"}], "artist": "Man\u00e1"}