{"songs": [{"title": "El Ganga Est\u00e1 Ah\u00ed", "album": "La Concha de Dio$", "year": "2017-08-09", "lyrics": "[Letra de \"El Ganga Est\u00e1 Ah\u00ed\"]\n\n[Intro]\n- \u00d3rale g\u00fcey, \u00bfy ad\u00f3nde est\u00e1 el Ganga?\n- Ac\u00e1 estoy\n- \u00bfAd\u00f3nde?\n- \u00a1Ac\u00e1 estoy!\n- Dime donde est\u00e1 el Ganga\n- \u00bfPues no lo ves Willy? El Ganga est\u00e1 ah\u00ed\n\nEl Ganga est\u00e1 ah\u00ed\nEl Ganga est\u00e1 ah\u00ed\nEl Ganga est\u00e1 ah\u00ed\nEl Ganga est\u00e1 ah\u00ed\nEl Ganga est\u00e1 ah\u00ed!\n\n[Outro]\n- Me va a tener que acompa\u00f1ar\n- \u00a1Pero soy inocente!", "image": "https://images.genius.com/9d15efaf7d7c2fdbf653382174d65a62.800x800x1.jpg"}], "artist": "Asspera"}