{"songs": [{"title": "El Charco", "album": "Americanos", "year": "1973-01-01", "lyrics": "[Letra de \"El Charco\"]\n\nUna gota cayo\nTalvez, el sol se este ocultando\nLloviendo mi dolor\nEs que el dia llego al fin\nEn que veo mi imagen\nEn un charco que pise\nLlueve y el charco se agrando\nAgua con olor salpica a los demas\nY ensucia\n\nUn amigo pasa y mira dentro de el\nCuidado conmigo que te mojo los pies\nY al regresar solo polvo y mugre quizas encontraras\nEl sol con sus rayos seco mi vanidad\n\nHoy a vuelto a llover\nTalvez, el agua este mas limpia\nQue ayer en el zanjon\nTodo se transformo\nEl sol no seca ya mi vida\nDescansa en el mar\n\nEs que su agua se elevo\nY del cielo a vuelto a caer\nRadiante\nTodos esos charcos que secandose estan\nSolo gota a gota en lluvias se armaran\nY nunca mas entre nuebes tristes el sol se ocultara\nPues sera el momento de la paz\n\nOooh si...\nSolamente paz...\nOooh si...", "image": "https://images.genius.com/38d1cf873ad2f189424ba4555a733d1e.1000x1000x1.jpg"}], "artist": "Contraluz"}