{"songs": [{"title": "Ella", "album": "Am\u00e9n!", "year": null, "lyrics": "Esta noche te quer\u00e9s drogar\nEsta no noche no sab\u00e9s que hacer\nLo que hab\u00edas pensado termin\u00f3 cuando me viste a mi\nEsta noche te quer\u00e9s drogar\nEsta no noche no sab\u00e9s que hacer\nLo que hab\u00edas pensado termin\u00f3 cuando me viste a mi\nY no pudiste resistirte a pensar mal\nVos no pudiste resistirte a pensar mal\n\u00bfPor qu\u00e9 no me dec\u00eds el asco que te doy?\nEl asco que te doy\n\u00bfPor qu\u00e9 no me dec\u00eds el asco que te doy?\nEl asco que te doy\nPediste por favor que te trague la tierra\nPuteaste muchas veces a Dios\nNo voy a detenerme no voy a perdonarte\nQuiero decirte algo que tengo para vos;\nAndate a la reputa madre que te pari\u00f3\nY no pudiste resistirte a pensar mal\nVos no pudiste resistirte a pensar mal\n\u00bfPor qu\u00e9 no me dec\u00eds el asco que te doy?\nEl asco que te doy...\n\u00bfPor qu\u00e9 no me dec\u00eds el asco que te doy?\nEl asco que te doy...\nLa amo y ella lo sabe\nLa amo y ella lo sabe", "image": "https://images.genius.com/0d394bd962416ae8924ec3253bff9c43.999x999x1.jpg"}], "artist": "Attaque 77"}