{"songs": [{"title": "Over and Over Again (Lost and Found)", "album": "Clap Your Hands Say Yeah", "year": "2005-09-13", "lyrics": "I heard it from a friend\nThe Revolution never happened\nSigh\nA little die\nNo more a child\nGoodbye\n\nNow where's the woolen sweater\nYou mentioned in the letter?\nImply\nThe other guy\nAnd scandalize the lion\n\nA clean shave in the morning\nAnd a full beard with no warning\nTime has gotten by on alibis and wine\n\nSuccess is so forbidding\nBut it makes me think I'm winning\nQuiet\nDim the lights\nAdopt another lifestyle\n\nCome come come on\nCome come come on\nCome come come on\nCome come come on\nCome come come on\nCome come come on\nCome come come\nOver and over again\n\nYou look like David Bowie\nBut you've nothing new to show me\nStart another fire\nAnd watch it slowly die", "image": "https://images.genius.com/5093829f616ec76ff4f6bf68f66663f4.1000x1000x1.jpg"}], "artist": "Clap Your Hands Say Yeah"}