{"songs": [{"title": "El Tesoro", "album": "La S\u00edntesis O\u2019Konor", "year": null, "lyrics": "[Letra de \"El Tesoro\"]\n\n[Verso 1]\nAh, paso todo el d\u00eda pensando en vos\nAh, \u00bfqu\u00e9 hay de malo en todo esto?\nAh, paso todo el d\u00eda pensando en vos\nAh, vos pens\u00e1s que pierdo el tiempo\n\n[Coro]\nPerd\u00f3n si estoy de nuevo ac\u00e1\nPens\u00e9 que hab\u00edas preguntado por m\u00ed\nMe gusta estar de nuevo ac\u00e1\nAunque no hayas preguntado por m\u00ed\nVoy a quedarme un poco ac\u00e1\nCuidarte siempre a vos en la derrota\nHasta el final, del final\n\n[Verso 2]\nAh, todo lo que hago es para vos\nAh, el tesoro se esta hundiendo\nAh, todo lo que hago es para vos\nAh, vos pens\u00e1s que pierdo el tiempo\n\n[Coro]\nPerd\u00f3n si estoy de nuevo ac\u00e1\nPens\u00e9 que hab\u00edas preguntado por m\u00ed\nMe gusta estar de nuevo ac\u00e1\nAunque no hayas preguntado por m\u00ed\nVoy a quedarme un poco ac\u00e1\nCuidarte siempre a vos en la derrota\nHasta el final, del final\n\n[Outro]\nEs la depresi\u00f3n sin \u00e9pica\nLa depresi\u00f3n sin \u00e9pica", "image": "https://images.genius.com/d3c0233e14cc8e73c1e73d8fb34b4b71.1000x1000x1.jpg"}], "artist": "El Mat\u00f3 a un Polic\u00eda Motorizado"}