{"songs": [{"title": "Permite se\u00f1or", "album": null, "year": null, "lyrics": "Perm\u00edteme se\u00f1or sentirte en mi vida\nPermite a mis mejillas ba\u00f1arse en l\u00e1grimas por ti\nPerm\u00edteme se\u00f1or tenerte en mi coraz\u00f3n\nPermite a m\u00ed existir ser solo para ti\n\nCoro:\nPerm\u00edteme se\u00f1or, se\u00f1or ser solo para ti\nY bajo tu manto de amor de amor perm\u00edteme vivir\nPerm\u00edteme un d\u00eda se\u00f1or volar hacia ti\nY tu bienvenida se\u00f1or perm\u00edteme o\u00edr\n\nPerm\u00edteme se\u00f1or sentir tus caricias\nPermite a mis mejillas ba\u00f1arse en l\u00e1grimas por ti\nPermite que al o\u00edr tu voz pueda escuchar\nPermite a mi vida ante ti derramar\n\nPerm\u00edteme tu cruz de cerca contemplar\nY tus pies heridos perm\u00edteme besar\nPerm\u00edteme en tu sangre mis heridas curar\nPerm\u00edteme tu cruz se\u00f1or abrazar", "image": "https://images.genius.com/93360ac649e0ecb394669aad4a150805.960x639x1.jpg"}], "artist": "Adamo"}