{"songs": [{"title": "Arreglo Zapatos", "album": "Paquetecuetes", "year": null, "lyrics": "Letra de \"Arreglo zapatos\"\n[Verso 1]\nQue es lo que se oye cuando \u00e9l pasa por aqu\u00ed\nQue es ese ruido que te invita a salir\nVa caminando con su caja por ah\u00ed\nA \u00e9l no le importa nunca tiene que fingir\nPor eso dice\n\n[Coro]\nArreglo zapatos, arreglo zapatos\nArreglo zapatos, arreglo zapatos\nArreglo zapatos, arreglo zapatos\nArreglo zapatos, arreglo zapatos\n\n[Verso 2]\nY me dices que siempre vas a regresar\nArreglo un, dos, tres, cuatro, cinco en un segundo est\u00e1n\nTodos caminan todos gastar\u00e1n sus suelas\nTodos caminan pero nadie como \u00e9l\nPor eso dice\n\n[Coro]\nArreglo zapatos, arreglo zapatos\nArreglo zapatos, arreglo zapatos\nArreglo zapatos, arreglo zapatos\nArreglo zapatos, arreglo zapatos\n\n[Puente]\nCamine y camine, y otra vez me encuentro caminando\nAqu\u00ed despacio camino con mi camisa al rev\u00e9s\nEsta bien no s\u00e9 para donde voy, no s\u00e9\nNo quise ser yo tambi\u00e9n, para donde vas no s\u00e9 tambi\u00e9n\n\n[Outro]\nY de tanto caminar va a desgastar sus zapatos\nY esas viejas suelas que trae tambi\u00e9n desde cuando no ha cambiado", "image": "https://images.genius.com/be0d8bce9b63c6dd07dc8afdd33673b3.499x499x1.jpg"}], "artist": "Malacates Trebol Shop"}